balinese_textpreprocessor/TextPreprocessor.py
balinese_textpreprocessor/__init__.py
balinese_textpreprocessor/utils.py
balinese_textpreprocessor/balinese_lemmatization/Lemmatization.py
balinese_textpreprocessor/balinese_lemmatization/LemmatizationRules.py
balinese_textpreprocessor/balinese_lemmatization/__init__.py
balinese_textpreprocessor/data/__init__.py
balinese_textpreprocessor/data/lemmatization/__init__.py
balinese_textpreprocessor/data/lemmatization/balivocab.txt
balinese_textpreprocessor/data/normalizedwords/__init__.py
balinese_textpreprocessor/data/normalizedwords/data.xlsx
balinese_textpreprocessor/data/stopwords/__init__.py
balinese_textpreprocessor/data/stopwords/data.txt
balinese_textpreprocessor-2.2.1.dist-info/LICENSE
balinese_textpreprocessor-2.2.1.dist-info/METADATA
balinese_textpreprocessor-2.2.1.dist-info/WHEEL
balinese_textpreprocessor-2.2.1.dist-info/top_level.txt
balinese_textpreprocessor-2.2.1.dist-info/RECORD
