Metadata-Version: 2.1
Name: balinese_textpreprocessor
Version: 2.2.1
Summary: A Python package for Balinese Text Preprocessing
Author: I Made Satria Bimantara
Author-email: satriabimantara.md@gmail.com
Keywords: Balinese,NLP,Text Preprocessing,Text Analysis
Classifier: Development Status :: 5 - Production/Stable
Classifier: Intended Audience :: Developers
Classifier: Intended Audience :: Science/Research
Classifier: License :: OSI Approved :: MIT License
Classifier: Programming Language :: Python :: 3
Classifier: Programming Language :: Python :: 3.8
Classifier: Operating System :: OS Independent
Classifier: Natural Language :: Indonesian
Classifier: Topic :: Text Processing :: Linguistic
Classifier: Topic :: Scientific/Engineering :: Artificial Intelligence
Requires-Python: >=3.8
License-File: LICENSE
Requires-Dist: pandas ==1.5.3
Requires-Dist: numpy ==1.24.2
Requires-Dist: balinese-library ==0.0.7
Requires-Dist: nltk ==3.9.1
Requires-Dist: openpyxl ==3.1.0
